artis_tomo/__init__.py
artis_tomo/version.py
artis_tomo/image/__init__.py
artis_tomo/image/alignment.py
artis_tomo/image/expand.py
artis_tomo/image/filter.py
artis_tomo/image/frame.py
artis_tomo/image/images.py
artis_tomo/image/process.py
artis_tomo/image/transformation.py
artis_tomo/io/__init__.py
artis_tomo/io/imageIO.py
artis_tomo/io/tomo.py
artis_tomo/io/image_formats/__init__.py
artis_tomo/io/image_formats/dvfile.py
artis_tomo/io/image_formats/image_fits.py
artis_tomo/io/image_formats/imageio_plugin_api.py
artis_tomo/io/image_formats/mistral_h5.py
artis_tomo/io/image_formats/mrcfile.py
artis_tomo/io/image_formats/tifffile.py
artis_tomo/math/__init__.py
artis_tomo/math/coordinates.py
artis_tomo/math/euler.py
artis_tomo/math/function.py
artis_tomo/math/prime.py
artis_tomo/math/statistics.py
artis_tomo/math/transforms.py
artis_tomo/math/fft/__init__.py
artis_tomo/math/fft/_backend.py
artis_tomo/math/fft/cufft.py
artis_tomo/math/fft/pyfftw.py
artis_tomo/math/fft/torchfft.py
artis_tomo/math/framework/__init__.py
artis_tomo/math/framework/_array.py
artis_tomo/math/framework/_cupy.py
artis_tomo/math/framework/_frame.py
artis_tomo/math/framework/_frameworks.py
artis_tomo/math/framework/_interface.py
artis_tomo/math/framework/_numpy.py
artis_tomo/math/framework/_torch.py
artis_tomo/programs/__init__.py
artis_tomo/programs/clfluoxr2d.py
artis_tomo/programs/clfluoxr3d.py
artis_tomo/programs/tomo_import_imod.py
artis_tomo/tomo/__init__.py
artis_tomo/tomo/alignment.py
artis_tomo/tomo/filter.py
artis_tomo/tomo/project.py
artis_tomo/tomo/recon.py
artis_tomo/tomo/tomogram.py
artis_tomo/tomo/utils.py
artis_tomo/tools/__init__.py
artis_tomo/tools/colorList.py
artis_tomo/tools/conversions.py
artis_tomo/tools/file.py
artis_tomo/tools/filter.py
artis_tomo/tools/imageProcess.py
artis_tomo/tools/metadataIO.py
artis_tomo/tools/parallel.py
artis_tomo/tools/system.py
artis_tomo/tools/transformGeometry.py
artis_tomo/utils/__init__.py
artis_tomo/utils/config.py
artis_tomo/utils/dict.py
artis_tomo-1.0.0.dist-info/AUTHORS.rst
artis_tomo-1.0.0.dist-info/LICENSE.rst
artis_tomo-1.0.0.dist-info/METADATA
artis_tomo-1.0.0.dist-info/WHEEL
artis_tomo-1.0.0.dist-info/entry_points.txt
artis_tomo-1.0.0.dist-info/top_level.txt
artis_tomo-1.0.0.dist-info/RECORD
