Metadata-Version: 2.1
Name: artis_tomo
Version: 1.0.0
Summary: Scientific Methods for tomography
Home-page: https://github.com/ALBA-Synchrotron-Methodology/artis_tomo
Author: Joaquín Otón, Josué Gómez
Author-email: joaquin.oton@gmail.com
License: GPLv3
Classifier: Development Status :: 4 - Beta
Classifier: Intended Audience :: Science/Research
Classifier: Topic :: Scientific/Engineering
Classifier: License :: OSI Approved :: GNU General Public License v3 or later (GPLv3+)
Classifier: Natural Language :: English
Classifier: Programming Language :: Python :: 3.7
Classifier: Programming Language :: Python :: 3.8
Classifier: Programming Language :: Python :: 3.9
Classifier: Programming Language :: Python :: 3.10
Classifier: Programming Language :: Python :: 3.11
Requires-Python: >=3.7
License-File: LICENSE.rst
License-File: AUTHORS.rst
Requires-Dist: numpy
Requires-Dist: matplotlib
Requires-Dist: numba ==0.59.1
Requires-Dist: scipy ==1.11.4
Requires-Dist: scikit-image
Requires-Dist: pyfftw ==0.13.1
Requires-Dist: joblib
Requires-Dist: mrcfile
Requires-Dist: mrc
Requires-Dist: h5py
Requires-Dist: imageio
Requires-Dist: pandas
Requires-Dist: pywavelets
Requires-Dist: transforms3d
Requires-Dist: tqdm
Requires-Dist: docopt
Requires-Dist: xmltodict
Requires-Dist: pyyaml
Provides-Extra: cupy
Requires-Dist: cupy ; extra == 'cupy'
